{
  "league": {
    "id": 128462,
    "name": "SuF"
  },
  "fetchedAt": "2026-07-12T10:39:56+00:00",
  "status": "ok",
  "message": "Stilling hentet.",
  "entries": [
    {
      "rank": 1,
      "managerName": "VikingPlaymaker",
      "teamName": "",
      "points": 547,
      "lastRoundPoints": 85
    },
    {
      "rank": 2,
      "managerName": "HC WIN",
      "teamName": "",
      "points": 545,
      "lastRoundPoints": 77
    },
    {
      "rank": 3,
      "managerName": "DanishNorseman",
      "teamName": "",
      "points": 498,
      "lastRoundPoints": 50
    },
    {
      "rank": 4,
      "managerName": "ESI1994",
      "teamName": "",
      "points": 462,
      "lastRoundPoints": 83
    },
    {
      "rank": 5,
      "managerName": "Sec United",
      "teamName": "",
      "points": 442,
      "lastRoundPoints": 67
    },
    {
      "rank": 6,
      "managerName": "Don-O",
      "teamName": "",
      "points": 427,
      "lastRoundPoints": 72
    },
    {
      "rank": 7,
      "managerName": "Testtesttest",
      "teamName": "",
      "points": 423,
      "lastRoundPoints": 70
    },
    {
      "rank": 8,
      "managerName": "rehpotsirhc",
      "teamName": "",
      "points": 409,
      "lastRoundPoints": 88
    },
    {
      "rank": 9,
      "managerName": "Anders Zaar",
      "teamName": "",
      "points": 406,
      "lastRoundPoints": 27
    },
    {
      "rank": 10,
      "managerName": "Hedge Fund Hooligans",
      "teamName": "",
      "points": 380,
      "lastRoundPoints": 34
    },
    {
      "rank": 11,
      "managerName": "Lukasworm",
      "teamName": "",
      "points": 379,
      "lastRoundPoints": 79
    },
    {
      "rank": 12,
      "managerName": "HvemkanAnnika",
      "teamName": "",
      "points": 364,
      "lastRoundPoints": 30
    },
    {
      "rank": 13,
      "managerName": "Aaquist",
      "teamName": "",
      "points": 356,
      "lastRoundPoints": 52
    },
    {
      "rank": 14,
      "managerName": "irs97",
      "teamName": "",
      "points": 353,
      "lastRoundPoints": 26
    },
    {
      "rank": 15,
      "managerName": "Doktor Svin",
      "teamName": "",
      "points": 343,
      "lastRoundPoints": 17
    },
    {
      "rank": 16,
      "managerName": "Carroev",
      "teamName": "",
      "points": 268,
      "lastRoundPoints": 18
    }
  ]
}